{
    "Name" : "代曜工程",
    "enName" : "DAIYAO Construction Co ., Ltd.",
    "number" : "0982-258-492",
    "numberLink" : "tel:+886-982258492",
    "lineLink" : "https://line.me/ti/p/eGdYQhJ6Kg",
    "fax" : "(02)2680-4388",
    "address" : "新北市樹林區三俊街194號",
    "addressLink" : "https://goo.gl/maps/J2Vh4FpzJUmbiM9n8",
    "mapIframe" : "https://www.google.com/maps/embed?pb=!1m18!1m12!1m3!1d3615.5503415691087!2d121.41644631537841!3d25.015390845190243!2m3!1f0!2f0!3f0!3m2!1i1024!2i768!4f13.1!3m3!1m2!1s0x34681d610af4bbf7%3A0xcf5bdb039f9afa67!2zMjM45paw5YyX5biC5qi55p6X5Y2A5LiJ5L-K6KGXMTk06Jmf!5e0!3m2!1szh-TW!2stw!4v1618197409744!5m2!1szh-TW!2stw"
}